MANIFEST.in
README.rst
setup.cfg
setup.py
deflicker/__init__.py
deflicker/__main__.py
deflicker.egg-info/PKG-INFO
deflicker.egg-info/SOURCES.txt
deflicker.egg-info/dependency_links.txt
deflicker.egg-info/entry_points.txt
deflicker.egg-info/requires.txt
deflicker.egg-info/top_level.txt