Metadata-Version: 1.1
Name: deflicker
Version: 0.1.1
Summary: Adjust the brightness of images for smooth timelapse videos
Home-page: http://github.com/maxnoe/timelapse-deflicker
Author: Maximilian Noethe
Author-email: maximilian.noethe@tu-dortmund.de
License: MIT
Keywords: image timelapse
Platform: UNKNOWN
Classifier: Development Status :: 4 - Beta
Classifier: Programming Language :: Python :: 3
Classifier: Programming Language :: Python :: 3.2
Classifier: Programming Language :: Python :: 3.3
Classifier: Programming Language :: Python :: 3.4
Classifier: Programming Language :: Python :: 3.5
